ether_mcp_server/__about__.py
ether_mcp_server/__init__.py
ether_mcp_server-0.0.1.dist-info/METADATA
ether_mcp_server-0.0.1.dist-info/WHEEL
ether_mcp_server-0.0.1.dist-info/licenses/LICENSE.txt
ether_mcp_server-0.0.1.dist-info/RECORD
