Metadata-Version: 2.4
Name: ether-mcp-server
Version: 0.0.1
Project-URL: Documentation, https://github.com/ming-der wang/ether-mcp-server#readme
Project-URL: Issues, https://github.com/ming-der wang/ether-mcp-server/issues
Project-URL: Source, https://github.com/ming-der wang/ether-mcp-server
Author-email: ming-der wang <mingderwang@me.com>
License-Expression: MIT
License-File: LICENSE.txt
Classifier: Development Status :: 4 - Beta
Classifier: Programming Language :: Python
Classifier: Programming Language :: Python :: 3.8
Classifier: Programming Language :: Python :: 3.9
Classifier: Programming Language :: Python :: 3.10
Classifier: Programming Language :: Python :: 3.11
Classifier: Programming Language :: Python :: 3.12
Classifier: Programming Language :: Python :: Implementation :: CPython
Classifier: Programming Language :: Python :: Implementation :: PyPy
Requires-Python: >=3.8
